airbyte_connector_models/__init__.py
airbyte_connector_models/py.typed
airbyte_connector_models/connectors/_internal/__init__.py
airbyte_connector_models/connectors/_internal/base_config.py
airbyte_connector_models/connectors/_internal/base_record.py
airbyte_connector_models/connectors/_internal/normalizer.py
airbyte_connector_models/connectors/airbyte/__init__.py
airbyte_connector_models/connectors/airbyte/source/__init__.py
airbyte_connector_models/connectors/airbyte/source/configuration.json
airbyte_connector_models/connectors/airbyte/source/configuration.py
airbyte_connector_models/connectors/airbyte/source/records/Connections.json
airbyte_connector_models/connectors/airbyte/source/records/Jobs.json
airbyte_connector_models/connectors/airbyte/source/records/Workspaces.json
airbyte_connector_models/connectors/airbyte/source/records/__init__.py
airbyte_connector_models/connectors/airbyte/source/records/connections.py
airbyte_connector_models/connectors/airbyte/source/records/jobs.py
airbyte_connector_models/connectors/airbyte/source/records/workspaces.py
airbyte_connector_models/connectors/dockerhub/__init__.py
airbyte_connector_models/connectors/dockerhub/source/__init__.py
airbyte_connector_models/connectors/dockerhub/source/configuration.json
airbyte_connector_models/connectors/dockerhub/source/configuration.py
airbyte_connector_models/connectors/dockerhub/source/records/__init__.py
airbyte_connector_models/connectors/dockerhub/source/records/docker_hub.json
airbyte_connector_models/connectors/dockerhub/source/records/docker_hub.py
airbyte_connector_models/connectors/duckdb/__init__.py
airbyte_connector_models/connectors/duckdb/destination/__init__.py
airbyte_connector_models/connectors/duckdb/destination/configuration.json
airbyte_connector_models/connectors/duckdb/destination/configuration.py
airbyte_connector_models/connectors/faker/__init__.py
airbyte_connector_models/connectors/faker/source/__init__.py
airbyte_connector_models-0.1.4.dist-info/METADATA
airbyte_connector_models-0.1.4.dist-info/WHEEL
airbyte_connector_models-0.1.4.dist-info/licenses/LICENSE
airbyte_connector_models-0.1.4.dist-info/RECORD
