Metadata-Version: 2.4
Name: airbyte-connector-models
Version: 0.1.4
Summary: Typed Pydantic models for Airbyte connectors
Project-URL: Homepage, https://github.com/airbytehq/airbyte-connector-models
Project-URL: Repository, https://github.com/airbytehq/airbyte-connector-models
Author-email: Airbyte <contact@airbyte.io>
License: MIT
License-File: LICENSE
Requires-Python: <3.13,>=3.10
Requires-Dist: airbyte-api<1.0,>=0.53.0
Requires-Dist: airbyte-cdk<8.0.0,>=7.3.9
Requires-Dist: pydantic<3.0,>=2.0
Requires-Dist: requests<3.0,>=2.31.0
Provides-Extra: dev
Requires-Dist: datamodel-code-generator<1.0,>=0.25.0; extra == 'dev'
Requires-Dist: poethepoet<1.0,>=0.26.1; extra == 'dev'
Requires-Dist: pyrefly>=0.42.0; extra == 'dev'
Requires-Dist: pytest<9.0,>=8.2.0; extra == 'dev'
Requires-Dist: ruff<1.0,>=0.8.2; extra == 'dev'
